helm_upgrade/__init__.py
helm_upgrade/app.py
helm_upgrade/cli.py
helm_upgrade-0.1.1.dist-info/entry_points.txt
helm_upgrade-0.1.1.dist-info/LICENSE
helm_upgrade-0.1.1.dist-info/WHEEL
helm_upgrade-0.1.1.dist-info/METADATA
helm_upgrade-0.1.1.dist-info/RECORD
