Metadata-Version: 2.1
Name: helm-upgrade
Version: 0.1.1
Summary: A Python CLI to manage Helm Chart dependencies
License: MIT
Author: Sarah Gibson
Author-email: drsarahlgibson@gmail.com
Requires-Python: >=3.8,<4.0
Classifier: License :: OSI Approved :: MIT License
Classifier: Programming Language :: Python :: 3
Classifier: Programming Language :: Python :: 3.10
Classifier: Programming Language :: Python :: 3.8
Classifier: Programming Language :: Python :: 3.9
Requires-Dist: bs4 (==0.0.1)
Requires-Dist: numpy (==1.22.3)
Requires-Dist: requests (==2.27.1)
Requires-Dist: ruamel.yaml (>=0.17.21,<0.18.0)
